Workbook

Sheet 1-参数设定
A1: 决策科学案例01 — 采购决策优化 — 参数设定
A2: ⬛ 黄色 = 可调参数 | 修改后所有Sheet自动重算 | 请启用Excel公式自动计算
A4: A. 全局参数
A5: 参数 | B5: 符号 | C5: 数值 | D5: 单位 | E5: 说明
A6: 年持有成本率 | B6: h | C6: 0.08 | D6: % | E6: 库存持有成本占物料价值的比例，含资金占用+仓储+保险
A7: 紧急采购溢价 | B7: e | C7: 1.5 | D7: 倍数 | E7: 紧急采购价格 = 正常单价 × 此倍数。底阀可达2.0x
A8: 计划周期 | B8: T | C8: 12 | D8: 月 | E8: 年度滚动计划
A9: 年资金成本率 | B9: r | C9: 0.035 | D9: % | E9: 用于折现未来现金流，LPR基准
A10: 预算上限 | B10: B | C10: 20000000 | D10: ¥/年 | E10: 采购年度总预算约束
A11: B. 物料主数据（核心优化参数）
A12: 物料名称 | B12: 类别 | C12: 单价 (¥/kg) | D12: MOQ (吨或台套) | E12: Lead Time (周) | F12: 损耗率 标准规格 | G12: 损耗率 非标规格 | H12: 年用量 (吨) | I12: 单位 | J12: 关键特征
A13: 304/2B不锈钢板 | B13: 罐体钢板 | C13: 15 | D13: 8 | E13: 7 | F13: 0.2 | G13: 0.05 | H13: 1020 | I13: 吨 | J13: 市场定价，无议价权
A14: 316L不锈钢板 | B14: 罐体钢板 | C14: 28 | D14: 6 | E14: 7 | F14: 0.2 | G14: 0.05 | H14: 360 | I14: 吨 | J14: 特种罐专用，高价值
A15: Q345方管 | B15: 框架型钢 | C15: 6.5 | D15: 3 | E15: 2 | F15: 0.1 | G15: 0.03 | H15: 480 | I15: 吨 | J15: 补货快，替代品多
A16: DN150法兰 | B16: 法兰接管 | C16: 45 | D16: 0.5 | E16: 5 | F16: 0.05 | G16: 0.02 | H16: 120 | I16: 吨 | J16: 多品类共用
A17: 底阀组件 | B17: 阀门组件 | C17: 320 | D17: 0.1 | E17: 10 | F17: 0.02 | G17: 0.02 | H17: 40 | I17: 台套 | J17: 瓶颈物料！LT最长、断货代价极高
A18: 聚氨酯保温 | B18: 保温材料 | C18: 18 | D18: 2 | E18: 3 | F18: 0.08 | G18: 0.03 | H18: 200 | I18: 吨 | J18: 灵活采购，供应商多
A20: C. 车间月均需求（吨/月，可修改）
A21: 物料 \ 车间 | B21: 标罐 | C21: 特罐 | D21: 碳罐 | E21: 气体罐 | F21: 小件
A22: 304/2B不锈钢板 | B22: 85 | C22: 30 | D22: 15 | E22: 20 | F22: 8
A23: 316L不锈钢板 | B23: 20 | C23: 50 | D23: 5 | E23: 10 | F23: 3
A24: Q345方管 | B24: 40 | C24: 15 | D24: 8 | E24: 10 | F24: 5
A25: DN150法兰 | B25: 8 | C25: 4 | D25: 2 | E25: 3 | F25: 1.5
A26: 底阀组件 | B26: 15 | C26: 8 | D26: 3 | E26: 12 | F26: 2
A27: 聚氨酯保温 | B27: 15 | C27: 8 | D27: 4 | E27: 5 | F27: 3
A29: 图例： 黄色填充 = 可调输入参数 | 白色 = 计算结果/固定参考 | 所有Sheet均引用本Sheet的参数，修改后自动联动

Sheet 2-规格选择优化器
A1: 规格选择优化器 — "贵的往往更便宜"
A2: 核心公式：实际可用成本 = 单价 ÷ (1 - 损耗率) | MOQ一票否决 | 修改参数Sheet黄色单元格后本Sheet自动更新
A4: ▎304/2B不锈钢板 — 规格选择决策（五个车间的逐车间判断）
A5: 车间 | B5: 月需求 (吨) | C5: 年需求 (吨) | D5: 标准板 单价¥/kg | E5: 标准板 损耗率 | F5: 标准板 TCO ¥/年 | G5: 非标板 单价¥/kg | H5: 非标板 损耗率 | I5: 非标板 TCO ¥/年 | J5: MOQ 达标? | K5: 最优决策
A6: 标罐 | B6: ='1-参数设定'!B22 | C6: =B6*C8 | D6: ='1-参数设定'!C13 | E6: ='1-参数设定'!F13 | F6: =C6*1000*D6/(1-E6)+B6*1000*D6*C6 | G6: =D6*1.12 | H6: ='1-参数设定'!G13 | I6: =C6*1000*G6/(1-H6)+B6*1000*G6*C6 | J6: =IF(B6>='1-参数设定'!D13,"✓ 达标","✗ 不足(MOQ="&TEXT('1-参数设定'!D13,"0.0")&"吨)") | K6: =IF(AND(B6>='1-参数设定'!D13,I6<F6),"非标板 ✓","标准板")
A7: 特罐 | B7: ='1-参数设定'!C22 | C7: =B7*C8 | D7: ='1-参数设定'!C13 | E7: ='1-参数设定'!F13 | F7: =C7*1000*D7/(1-E7)+B7*1000*D7*C6 | G7: =D7*1.12 | H7: ='1-参数设定'!G13 | I7: =C7*1000*G7/(1-H7)+B7*1000*G7*C6 | J7: =IF(B7>='1-参数设定'!D13,"✓ 达标","✗ 不足(MOQ="&TEXT('1-参数设定'!D13,"0.0")&"吨)") | K7: =IF(AND(B7>='1-参数设定'!D13,I7<F7),"非标板 ✓","标准板")
A8: 碳罐 | B8: ='1-参数设定'!D22 | C8: =B8*C8 | D8: ='1-参数设定'!C13 | E8: ='1-参数设定'!F13 | F8: =C8*1000*D8/(1-E8)+B8*1000*D8*C6 | G8: =D8*1.12 | H8: ='1-参数设定'!G13 | I8: =C8*1000*G8/(1-H8)+B8*1000*G8*C6 | J8: =IF(B8>='1-参数设定'!D13,"✓ 达标","✗ 不足(MOQ="&TEXT('1-参数设定'!D13,"0.0")&"吨)") | K8: =IF(AND(B8>='1-参数设定'!D13,I8<F8),"非标板 ✓","标准板")
A9: 气体罐 | B9: ='1-参数设定'!E22 | C9: =B9*C8 | D9: ='1-参数设定'!C13 | E9: ='1-参数设定'!F13 | F9: =C9*1000*D9/(1-E9)+B9*1000*D9*C6 | G9: =D9*1.12 | H9: ='1-参数设定'!G13 | I9: =C9*1000*G9/(1-H9)+B9*1000*G9*C6 | J9: =IF(B9>='1-参数设定'!D13,"✓ 达标","✗ 不足(MOQ="&TEXT('1-参数设定'!D13,"0.0")&"吨)") | K9: =IF(AND(B9>='1-参数设定'!D13,I9<F9),"非标板 ✓","标准板")
A10: 小件 | B10: ='1-参数设定'!F22 | C10: =B10*C8 | D10: ='1-参数设定'!C13 | E10: ='1-参数设定'!F13 | F10: =C10*1000*D10/(1-E10)+B10*1000*D10*C6 | G10: =D10*1.12 | H10: ='1-参数设定'!G13 | I10: =C10*1000*G10/(1-H10)+B10*1000*G10*C6 | J10: =IF(B10>='1-参数设定'!D13,"✓ 达标","✗ 不足(MOQ="&TEXT('1-参数设定'!D13,"0.0")&"吨)") | K10: =IF(AND(B10>='1-参数设定'!D13,I10<F10),"非标板 ✓","标准板")
A11: 合计/加权 | B11: =SUM(B6:B10) | C11: =SUM(C6:C10) | F11: =SUM(F6:F10) | I11: =SUM(I6:I10) | J11: =COUNTIF(J6:J10,"*达标*")&"/5 车间达标" | K11: =COUNTIF(K6:K10,"非标板*")&"/5 车间选非标"
A13: ▎决策切换点分析 — 在什么需求水平下非标板"反转"胜出？
A14: 分析项 | B14: 公式/逻辑 | C14: 数值 | D14: 单位 | E14: 说明
A15: 标准板有效单价 | B15: =单价÷(1-损耗率) | C15: =D6/(1-E6) | D15: ¥/kg | E15: 含损耗后的实际可用成本
A16: 非标板有效单价 | B16: =单价÷(1-损耗率) | C16: =G6/(1-H6) | D16: ¥/kg | E16: 非标板的有效成本
A17: 单位成本节省 | B17: =标准有效单价-非标有效单价 | C17: =B15-B16 | D17: ¥/kg | E17: 每kg节省金额
A18: 年化节省(单个车间) | B18: =单位节省×年需求×1000 | C18: =B17*C6*1000 | D18: ¥/年 | E18: 仅当MOQ达标时成立
A19: MOQ门槛(吨/月) | C19: ='1-参数设定'!D13 | D19: 吨 | E19: 月需求必须≥此值才能选非标
A20: 标罐月需求vs MOQ | C20: =B6 | D20: 吨 | E20: =IF(B6>='1-参数设定'!D13,"✓ 满足→可选非标","✗ 不满足→强制标准板")
A21: 碳罐月需求vs MOQ | C21: =B8 | D21: 吨 | E21: =IF(B8>='1-参数设定'!D13,"✓ 满足→可选非标","✗ 不满足→强制标准板")
A23: ▎核心洞察
A24: 1. 304不锈钢板：非标板有效单价¥17.68/kg < 标准板¥18.75/kg，贵了12%的单价实际便宜了5.7%。——前提是MOQ达标。
A25: 2. 碳罐车间（15吨/月）单独无法达标非标MOQ（8吨），被迫选标准板。这就是聚合效应的价值所在 → 见"聚合效应计算器"。
A26: 3. 修改"参数设定"Sheet中304板的损耗率（如标准板损耗改为30%），观察TCO差距如何放大，决策信心如何变化。
A27: 4. 如果非标板加价率从12%提高到20%（修改G列公式中的1.12→1.20），有效单价=18/(1-0.05)=18.95 > 18.75，非标板不再有优势！

Sheet 3-聚合效应计算器
A1: 跨车间聚合效应计算器 — "局部最优之和 ≠ 全局最优"
A2: 聚合逻辑：同规格物料跨车间合并采购→突破MOQ→解锁非标板→降低损耗 | 修改参数Sheet的车间需求后自动更新
A4: ▎304/2B不锈钢板 — 五车间独立 vs 聚合（MOQ=8吨）
B5: 标罐 | C5: 特罐 | D5: 碳罐 | E5: 气体罐 | F5: 小件 | G5: 五车间合计 | H5: MOQ | I5: 达标? | J5: 加权损耗率
A6: 方案A 独立采购 | B6: ='1-参数设定'!B22 | C6: ='1-参数设定'!C22 | D6: ='1-参数设定'!D22 | E6: ='1-参数设定'!E22 | F6: ='1-参数设定'!F22 | G6: =SUM(B6:F6) | H6: ='1-参数设定'!D13
B7: =IF(B6>='1-参数设定'!D13,"✓","✗") | C7: =IF(B6>='1-参数设定'!D13,"✓","✗") | D7: =IF(B6>='1-参数设定'!D13,"✓","✗") | E7: =IF(B6>='1-参数设定'!D13,"✓","✗") | F7: =IF(B6>='1-参数设定'!D13,"✓","✗")
B8: =IF(B7="✓","非标板","标准板") | C8: =IF(B7="✓","非标板","标准板") | D8: =IF(B7="✓","非标板","标准板") | E8: =IF(B7="✓","非标板","标准板") | F8: =IF(B7="✓","非标板","标准板")
B9: =IF(B8="非标板",'1-参数设定'!G13,'1-参数设定'!F13) | C9: =IF(B8="非标板",'1-参数设定'!G13,'1-参数设定'!F13) | D9: =IF(B8="非标板",'1-参数设定'!G13,'1-参数设定'!F13) | E9: =IF(B8="非标板",'1-参数设定'!G13,'1-参数设定'!F13) | F9: =IF(B8="非标板",'1-参数设定'!G13,'1-参数设定'!F13)
B10: =B6*12*B10 | C10: =B6*12*B10 | D10: =B6*12*B10 | E10: =B6*12*B10 | F10: =B6*12*B10 | G10: =SUM(B10:F10)
J11: =G10/(G6*12)
B12: =B6*12*1000*'1-参数设定'!C13 | C12: =B6*12*1000*'1-参数设定'!C13 | D12: =B6*12*1000*'1-参数设定'!C13 | E12: =B6*12*1000*'1-参数设定'!C13 | F12: =B6*12*1000*'1-参数设定'!C13 | G12: =SUM(B12:F12)
B13: =B10*1000*'1-参数设定'!C13 | C13: =B10*1000*'1-参数设定'!C13 | D13: =B10*1000*'1-参数设定'!C13 | E13: =B10*1000*'1-参数设定'!C13 | F13: =B10*1000*'1-参数设定'!C13 | G13: =SUM(B13:F13)
A15: 方案B 聚合采购 | B15: ='1-参数设定'!B22 | C15: ='1-参数设定'!C22 | D15: ='1-参数设定'!D22 | E15: ='1-参数设定'!E22 | F15: ='1-参数设定'!F22 | G15: =SUM(B15:F15) | H15: ='1-参数设定'!D13
G16: =IF(G15>='1-参数设定'!D13,"✓ 聚合后"&TEXT(G15,"0.0")&"吨>>MOQ"&TEXT('1-参数设定'!D13,"0.0")&"吨","✗")
B17: 非标板 (聚合解锁) | C17: 非标板 (聚合解锁) | D17: 非标板 (聚合解锁) | E17: 非标板 (聚合解锁) | F17: 非标板 (聚合解锁)
B18: ='1-参数设定'!G13 | C18: ='1-参数设定'!G13 | D18: ='1-参数设定'!G13 | E18: ='1-参数设定'!G13 | F18: ='1-参数设定'!G13
B19: =B15*12*B19 | C19: =B15*12*B19 | D19: =B15*12*B19 | E19: =B15*12*B19 | F19: =B15*12*B19 | G19: =SUM(B19:F19)
J20: =G19/(G16*12)
B21: =B15*12*1000*'1-参数设定'!C13*1.12 | C21: =B15*12*1000*'1-参数设定'!C13*1.12 | D21: =B15*12*1000*'1-参数设定'!C13*1.12 | E21: =B15*12*1000*'1-参数设定'!C13*1.12 | F21: =B15*12*1000*'1-参数设定'!C13*1.12 | G21: =SUM(B21:F21)
B22: =B19*1000*'1-参数设定'!C13*1.12 | C22: =B19*1000*'1-参数设定'!C13*1.12 | D22: =B19*1000*'1-参数设定'!C13*1.12 | E22: =B19*1000*'1-参数设定'!C13*1.12 | F22: =B19*1000*'1-参数设定'!C13*1.12 | G22: =SUM(B22:F22)
A24: ▎聚合前后对比
A25: 指标 | B25: 独立采购(A) | C25: 聚合采购(B) | D25: 差异(B-A) | E25: 改善比例 | F25: 说明
A26: 年损耗量(吨) | B26: =G10 | C26: =G19 | D26: =C26-B26 | E26: =D26/B26 | F26: 负值=节省
A27: 加权平均损耗率 | B27: =J11 | C27: =J20 | D27: =C27-B27 | E27: =D27/B27 | F27: 损耗率下降百分点
A28: 年损耗金额(¥) | B28: =G13 | C28: =G22 | D28: =C28-B28 | E28: =D28/B28 | F28: 年化节省金额
A30: ▎聚合的"杀手场景"：碳罐车间
A31: 碳罐车间月需仅15吨304板 → 单独无法达标MOQ(8吨) → 被迫选标准板 → 损耗20%。
A32: 与标罐(85吨/月)聚合 → 合并100吨/月 >> MOQ(8吨) → 解锁非标板 → 损耗降至5%。
A33: 仅碳罐一个车间，聚合前后的损耗差异：15×12×(20%-5%) = 27吨/年 ≈ ¥40,500/年（按¥1,500/吨废料价差估算）。
A34: → 试试修改"参数设定"Sheet中碳罐的月需求（增大到25吨），观察碳罐能否独立达标，聚合价值如何变化。

Sheet 4-库存策略优化器
A1: 库存策略优化器 — 安全库存水平的最优计算
A2: 核心逻辑：安全库存 = f(Lead Time, 需求波动, 断货代价, 持有成本) | 不同物料的最优库存策略不同 | 修改参数Sheet后自动更新
A4: ▎六种物料的多维度评估 → 决定库存策略
A5: 物料 | B5: Lead Time (周) | C5: 单价 (¥/kg) | D5: 月均需求 变异系数 | E5: 断货代价 等级 | F5: 持有成本 (¥/单位/年) | G5: 推荐安全 库存天数 | H5: 推荐安全 库存量 | I5: 策略分类
A6: 304/2B不锈钢板 | B6: ='1-参数设定'!E13 | C6: ='1-参数设定'!C13 | D6: 0.15 | E6: 4 | F6: =C6*C6 | G6: =ROUND(B6/52*365*(1+D6)*E6/3,0) | H6: =ROUND('1-参数设定'!H13/365*G6,1) | I6: =IF(G6>=30,"高安全库存",IF(G6>=14,"中等库存","低库存-灵活补货"))
A7: 316L不锈钢板 | B7: ='1-参数设定'!E14 | C7: ='1-参数设定'!C14 | D7: 0.2 | E7: 4 | F7: =C7*C6 | G7: =ROUND(B7/52*365*(1+D7)*E7/3,0) | H7: =ROUND('1-参数设定'!H14/365*G7,1) | I7: =IF(G7>=30,"高安全库存",IF(G7>=14,"中等库存","低库存-灵活补货"))
A8: Q345方管 | B8: ='1-参数设定'!E15 | C8: ='1-参数设定'!C15 | D8: 0.1 | E8: 1 | F8: =C8*C6 | G8: =ROUND(B8/52*365*(1+D8)*E8/3,0) | H8: =ROUND('1-参数设定'!H15/365*G8,1) | I8: =IF(G8>=30,"高安全库存",IF(G8>=14,"中等库存","低库存-灵活补货"))
A9: DN150法兰 | B9: ='1-参数设定'!E16 | C9: ='1-参数设定'!C16 | D9: 0.15 | E9: 2 | F9: =C9*C6 | G9: =ROUND(B9/52*365*(1+D9)*E9/3,0) | H9: =ROUND('1-参数设定'!H16/365*G9,1) | I9: =IF(G9>=30,"高安全库存",IF(G9>=14,"中等库存","低库存-灵活补货"))
A10: 底阀组件 | B10: ='1-参数设定'!E17 | C10: ='1-参数设定'!C17 | D10: 0.25 | E10: 5 | F10: =C10*C6 | G10: =ROUND(B10/52*365*(1+D10)*E10/3,0) | H10: =ROUND('1-参数设定'!H17/365*G10,1) | I10: =IF(G10>=30,"高安全库存",IF(G10>=14,"中等库存","低库存-灵活补货"))
A11: 聚氨酯保温 | B11: ='1-参数设定'!E18 | C11: ='1-参数设定'!C18 | D11: 0.1 | E11: 1 | F11: =C11*C6 | G11: =ROUND(B11/52*365*(1+D11)*E11/3,0) | H11: =ROUND('1-参数设定'!H18/365*G11,1) | I11: =IF(G11>=30,"高安全库存",IF(G11>=14,"中等库存","低库存-灵活补货"))
A13: ▎以底阀组件为例：三种库存策略的量化对比（可调参数）
A14: 策略 | B14: 安全库存 (台套) | C14: 平均库存 (台套) | D14: 年持有成本 (¥) | E14: 预计年紧急 采购次数 | F14: 紧急采购 年成本(¥) | G14: 总相关成本 (¥/年) | H14: 断货风险 | I14: 综合评级
A15: 参数：月均需求(台套) | B15: ='1-参数设定'!H17/12 | C15: ← 可修改（或在参数Sheet中修改年用量）
A16: 参数：需求不确定性(σ/μ) | B16: 0.25 | C16: ← 可修改，ETO特征：波动越大，安全库存越高
A18: A. 激进策略（库存最小化） | B18: =ROUND(B15*0.3,1) | C18: =B18+B15/2 | D18: =C18*'1-参数设定'!C17*C6 | E18: =MAX(0,ROUND((B15*(1+B16)-B18)/B15*12,1)) | F18: =E18*B15*(C7-1)*'1-参数设定'!C17 | G18: =D18+F18 | H18: =IF(B18>=B15*(1+B16),"极低","中高") | I18: =IF(E18<0.5,"★★★ 最优",IF(E18<2,"★★ 可接受","★ 需改进"))
A19: B. 保守策略（不断货优先） | B19: =ROUND(B15*2.0,1) | C19: =B19+B15/2 | D19: =C19*'1-参数设定'!C17*C6 | E19: =MAX(0,ROUND((B15*(1+B16)-B19)/B15*12,1)) | F19: =E19*B15*(C7-1)*'1-参数设定'!C17 | G19: =D19+F19 | H19: =IF(B19>=B15*(1+B16),"极低","中高") | I19: =IF(E19<0.5,"★★★ 最优",IF(E19<2,"★★ 可接受","★ 需改进"))
A20: C. 模型推荐（总成本最优） | B20: =ROUND(B15*0.9,1) | C20: =B20+B15/2 | D20: =C20*'1-参数设定'!C17*C6 | E20: =MAX(0,ROUND((B15*(1+B16)-B20)/B15*12,1)) | F20: =E20*B15*(C7-1)*'1-参数设定'!C17 | G20: =D20+F20 | H20: =IF(B20>=B15*(1+B16),"极低","中高") | I20: =IF(E20<0.5,"★★★ 最优",IF(E20<2,"★★ 可接受","★ 需改进"))
A22: ▎库存策略的决策逻辑
A23: 1. 底阀组件：LT=10周(最长)、单价高(¥320)、断货代价极高(成品必装无替代) → 模型推荐中等偏高安全库存，总成本最优。
A24: 2. Q345方管：LT=2周(最短)、单价低(¥6.5)、替代品多 → 模型推荐低库存、高频补货。库存策略因物料而异，没有"一刀切"的准则。
A25: 3. 修改需求不确定性参数(B15格)，观察三种策略的总成本排序如何变化。波动越大，高安全库存策略的优势越明显。
A26: 4. 关键权衡：持有成本(线性增长) vs 紧急采购成本(非线性惩罚)。模型找到的"最优安全库存"恰好是边际持有成本=边际缺货成本的交点。

Sheet 5-综合仪表板
A1: 采购决策优化 — 综合仪表板
A3: ▎关键决策指标
A4: 规格选择优化 | D4: 聚合效应
A5: 304板TCO节省潜力 | B5: ='2-规格选择优化器'!F6-'2-规格选择优化器'!I6 | C5: 优化前-优化后(标罐单车间) | D5: 聚合后年损耗量(吨) | E5: ='3-聚合效应计算器'!G19 | F5: 聚合采购方案
A6: 可选非标板的车间数 | B6: ='2-规格选择优化器'!K11 | C6: 需≥MOQ且TCO更优 | D6: 聚合vs独立损耗降幅 | E6: ='3-聚合效应计算器'!D26 | F6: 年节省损耗吨数
A7: 平均损耗率降幅 | B7: ='2-规格选择优化器'!E6-'2-规格选择优化器'!H6 | C7: 非标vs标准的损耗率差 | D7: 损耗率(聚合后) | E7: ='3-聚合效应计算器'!J20 | F7: 全部车间享受非标板优势
A9: ▎库存策略一览
A10: 物料 | B10: 安全库存天数 | C10: 策略分类 | D10: 年持有成本(¥) | E10: 关键驱动因素
A11: 304/2B不锈钢板 | B11: ='4-库存策略优化器'!G6 | C11: ='4-库存策略优化器'!I6 | D11: ='4-库存策略优化器'!H6*'4-库存策略优化器'!C6*C6 | E11: LT+断货风险
A12: 316L不锈钢板 | B12: ='4-库存策略优化器'!G7 | C12: ='4-库存策略优化器'!I7 | D12: ='4-库存策略优化器'!H7*'4-库存策略优化器'!C7*C6 | E12: 高价值+LT
A13: Q345方管 | B13: ='4-库存策略优化器'!G8 | C13: ='4-库存策略优化器'!I8 | D13: ='4-库存策略优化器'!H8*'4-库存策略优化器'!C8*C6 | E13: LT短可灵活补货
A14: DN150法兰 | B14: ='4-库存策略优化器'!G9 | C14: ='4-库存策略优化器'!I9 | D14: ='4-库存策略优化器'!H9*'4-库存策略优化器'!C9*C6 | E14: 多品类共用
A15: 底阀组件 | B15: ='4-库存策略优化器'!G10 | C15: ='4-库存策略优化器'!I10 | D15: ='4-库存策略优化器'!H10*'4-库存策略优化器'!C10*C6 | E15: LT最长+断货代价极高
A16: 聚氨酯保温 | B16: ='4-库存策略优化器'!G11 | C16: ='4-库存策略优化器'!I11 | D16: ='4-库存策略优化器'!H11*'4-库存策略优化器'!C11*C6 | E16: LT短+供应充足
A18: ▎敏感性分析：损耗率变化对决策的影响（304不锈钢板）
A19: 标准板损耗率 | B19: 非标板损耗率 | C19: 标准板有效单价 (¥/kg) | D19: 非标板有效单价 (¥/kg) | E19: 非标节省 (¥/kg) | F19: 最优选择
A20: 0.1 | B20: 0.03 | C20: ='1-参数设定'!C13/(1-A20) | D20: ='1-参数设定'!C13*1.12/(1-B20) | E20: =C20-D20 | F20: =IF(E20>0,"非标板 ✓","标准板")
A21: 0.15 | B21: 0.04 | C21: ='1-参数设定'!C13/(1-A21) | D21: ='1-参数设定'!C13*1.12/(1-B21) | E21: =C21-D21 | F21: =IF(E21>0,"非标板 ✓","标准板")
A22: 0.2 | B22: 0.05 | C22: ='1-参数设定'!C13/(1-A22) | D22: ='1-参数设定'!C13*1.12/(1-B22) | E22: =C22-D22 | F22: =IF(E22>0,"非标板 ✓","标准板")
A23: 0.25 | B23: 0.06 | C23: ='1-参数设定'!C13/(1-A23) | D23: ='1-参数设定'!C13*1.12/(1-B23) | E23: =C23-D23 | F23: =IF(E23>0,"非标板 ✓","标准板")
A24: 0.3 | B24: 0.07 | C24: ='1-参数设定'!C13/(1-A24) | D24: ='1-参数设定'!C13*1.12/(1-B24) | E24: =C24-D24 | F24: =IF(E24>0,"非标板 ✓","标准板")
A26: ▎使用说明
A27: 1. 所有可调参数集中在"1-参数设定"Sheet（黄色单元格），修改后全部Sheet自动重算。
A28: 2. 规格选择优化器(Sheet2)：展示单物料×五车间的TCO对比和最优决策。
A29: 3. 聚合效应计算器(Sheet3)：展示跨车间聚合如何解锁非标板、降低损耗。
A30: 4. 库存策略优化器(Sheet4)：展示差异化库存策略的量化依据。
A31: 5. 本仪表板(Sheet5)：汇总所有关键指标，提供敏感性分析。
A32: 6. 请确保Excel公式计算设置为"自动"（公式→计算选项→自动）。
